setup.cfg
setup.py
docker_zabbix_sender/RWLock.py
docker_zabbix_sender/__init__.py
docker_zabbix_sender/collector.py
docker_zabbix_sender/endpoint.py
docker_zabbix_sender/stats.py
docker_zabbix_sender/version.py
docker_zabbix_sender/zabbix_sender.py
docker_zabbix_sender.egg-info/PKG-INFO
docker_zabbix_sender.egg-info/SOURCES.txt
docker_zabbix_sender.egg-info/dependency_links.txt
docker_zabbix_sender.egg-info/entry_points.txt
docker_zabbix_sender.egg-info/not-zip-safe
docker_zabbix_sender.egg-info/pbr.json
docker_zabbix_sender.egg-info/requires.txt
docker_zabbix_sender.egg-info/top_level.txt