Metadata-Version: 1.1
Name: docker-zabbix-sender
Version: 0.3.2
Summary: Push Docker containers statistics to Zabbix efficiently
Home-page: https://github.com/dockermeetupsinbordeaux/docker-zabbix-sender
Author: Tristan Carel
Author-email: tristan.carel@gmail.com
License: Apache license version 2.0
Download-URL: https://github.com/dockermeetupsinbordeaux/docker-zabbix-sender/tarball/v0.3.2
Keywords: docker zabbix monitoring
Platform: UNKNOWN
Classifier: Development Status :: 4 - Beta
Classifier: Environment :: Other Environment
Classifier: Intended Audience :: Developers
Classifier: Operating System :: OS Independent
Classifier: Programming Language :: Python
Classifier: Programming Language :: Python :: 2.6
Classifier: Programming Language :: Python :: 2.7
Classifier: Programming Language :: Python :: 3.2
Classifier: Programming Language :: Python :: 3.3
Classifier: Programming Language :: Python :: 3.4
Classifier: Topic :: Utilities
Classifier: License :: OSI Approved :: Apache Software License
